market_analyzer/__init__.py
market_analyzer/candle_gap_analysis.py
market_analyzer/chart_patterns.py
market_analyzer/fibonacci_levels.py
market_analyzer/ltp_near_gaps.py
market_analyzer/run_analysis.py
market_analyzer/smc_analysis.py
market_analyzer/smc_screener.py
market_analyzer/stock_data_manager.py
market_analyzer/support_resistance.py
market_analyzer-0.0.2.dist-info/METADATA
market_analyzer-0.0.2.dist-info/WHEEL
market_analyzer-0.0.2.dist-info/top_level.txt
market_analyzer-0.0.2.dist-info/RECORD
