Metadata-Version: 2.4
Name: market_analyzer
Version: 0.0.2
Summary: A powerful toolkit for Smart Money Concepts (SMC) analysis and stocks (Gaps, fib, S/R, chart_patterns) analysis.
Author-email: Prasad <mr.xprasadx@gmail.com>
Requires-Python: >=3.9
Requires-Dist: yfinance>=0.2.36
Requires-Dist: pandas>=2.0.0
Requires-Dist: numpy>=1.24.0
Requires-Dist: matplotlib>=3.7.0
Requires-Dist: scipy>=1.10.0
Requires-Dist: tqdm>=4.65.0
Requires-Dist: gspread>=5.10.0
Requires-Dist: google-auth>=2.20.0
Requires-Dist: oauth2client>=4.1.3
Requires-Dist: prettytable>=3.7.0
Requires-Dist: mplfinance>=0.12.9b7
